{
  "users": [
    {
      "id": "5638",
      "email": "abdullaevadil2007@gmail.com",
      "name": "dilrukh",
      "surname": "abdullaeva",
      "password": "1234"
    }
  ],
  "wallets": [
    {
      "id": "0.9022087324823747",
      "created_at": "26.03.2024",
      "updated_at": "26.03.2024",
      "user_id": "5638",
      "name": "rrrrrrrrrr",
      "currency": "AED",
      "balance": 7
    }
  ],
  "transictions": [
    {
      "id": "c6a2",
      "created_at": "26.03.2024",
      "updated_at": "14:42:18",
      "time": "14:42:18",
      "user_id": "5638",
      "wallet": {
        "created_at": "26.03.2024",
        "updated_at": "26.03.2024",
        "name": "rrrrrrrrrr",
        "currency": "AED",
        "balance": 7
      },
      "total": "70",
      "category": "car",
      "description": "sbf",
      "wallet_id": "0.9022087324823747"
    }
  ]
}